HiReS/__init__.py
HiReS/cli.py
HiReS/config.py
HiReS/pipeline.py
HiReS/anno/__init__.py
HiReS/anno/datatypes.py
HiReS/anno/nms.py
HiReS/anno/ops.py
HiReS/anno/parser.py
HiReS/ios/__init__.py
HiReS/ios/chunker.py
HiReS/ios/plotting.py
HiReS/ios/writer.py
HiReS/ios/yolo_predictor.py
hireseg-0.3.0.dist-info/METADATA
hireseg-0.3.0.dist-info/WHEEL
hireseg-0.3.0.dist-info/entry_points.txt
hireseg-0.3.0.dist-info/top_level.txt
hireseg-0.3.0.dist-info/RECORD
