Metadata-Version: 2.4
Name: HiReSeg
Version: 0.3.0
Summary: High-Resolution Image Segmentation Pipeline
Author-email: Stylianos Mavrianos <stylianosmavrianos@gmail.com>
Project-URL: Homepage, https://github.com/StevetheGreek97/HiReS.git
Requires-Python: >=3.10
Requires-Dist: ultralytics>=8.0.0
Requires-Dist: Pillow>=10.0.0
Requires-Dist: shapely>=2.0.0
Requires-Dist: numpy>=1.25.0
Requires-Dist: matplotlib>=3.8.0
Requires-Dist: tqdm>=4.66.0
